pylinks/__init__.py
pylinks/_settings.py
pylinks/http.py
pylinks/media_type.py
pylinks/string.py
pylinks/url.py
pylinks/api/__init__.py
pylinks/api/doi.py
pylinks/api/github.py
pylinks/api/orcid.py
pylinks/api/zenodo.py
pylinks/exception/__init__.py
pylinks/exception/api.py
pylinks/exception/base.py
pylinks/exception/media_type.py
pylinks/exception/uri.py
pylinks/site/__init__.py
pylinks/site/binder.py
pylinks/site/conda.py
pylinks/site/github.py
pylinks/site/lib_io.py
pylinks/site/pypi.py
pylinks/site/readthedocs.py
pylinks/uri/__init__.py
pylinks/uri/data.py
pylinks-0.1.0.dist-info/METADATA
pylinks-0.1.0.dist-info/WHEEL
pylinks-0.1.0.dist-info/top_level.txt
pylinks-0.1.0.dist-info/RECORD
